mapon/__init__.py
mapon/config.py
mapon/exceptions.py
mapon/logging.py
mapon/mapon.py
mapon/sqlite_keywords.txt
mapon/util.py
tests/__init__.py
tests/orders1.txt
tests/round-table.txt
tests/test.py
tests/test_mapon.py
tests/test_util.py
mapon-0.0.9.dist-info/LICENSE
mapon-0.0.9.dist-info/METADATA
mapon-0.0.9.dist-info/WHEEL
mapon-0.0.9.dist-info/top_level.txt
mapon-0.0.9.dist-info/RECORD
