Metadata-Version: 2.1
Name: mapon
Version: 0.0.9
Summary: A data wrangling tool
Home-page: https://github.com/nalssee/mapon.git
Author: nalssee
Author-email: jinisrolling@gmail.com
License: MIT
Platform: UNKNOWN
